setup.py
PySimprocSP/__init__.py
PySimprocSP/parser.py
PySimprocSP/settings.py
PySimprocSP.egg-info/PKG-INFO
PySimprocSP.egg-info/SOURCES.txt
PySimprocSP.egg-info/dependency_links.txt
PySimprocSP.egg-info/not-zip-safe
PySimprocSP.egg-info/requires.txt
PySimprocSP.egg-info/top_level.txt