Metadata-Version: 1.0
Name: PySimprocSP
Version: 0.1
Summary: Get process details in the Simproc system on the            website of the city of São Paulo.
Home-page: http://github.com/luisrpp/python-simproc-sp
Author: Luis Roberto Pereira de Paula
Author-email: luisrpp@gmail.com
License: MIT
Platform: UNKNOWN
